<?xml version="1.0" encoding="UTF-8"?>
<beans xmlns="http://www.springframework.org/schema/beans"
	   xmlns:xsi="http://www.w3.org/2001/XMLSchema-instance"
	   xmlns:aop="http://www.springframework.org/schema/aop"
	   xmlns:tx="http://www.springframework.org/schema/tx"
	   xsi:schemaLocation="
	   http://www.springframework.org/schema/beans http://www.springframework.org/schema/beans/spring-beans-2.0.xsd
	   http://www.springframework.org/schema/tx http://www.springframework.org/schema/tx/spring-tx-2.0.xsd
	   http://www.springframework.org/schema/aop http://www.springframework.org/schema/aop/spring-aop-2.0.xsd">
	

	<!-- Binding Properties -->
	<bean id="propertyConfigurer" class="org.springframework.beans.factory.config.PropertyPlaceholderConfigurer">
		<property name="location"><value>WEB-INF/properties/jdbc.properties</value></property>
	</bean>

	<bean id="messageSource" class="org.springframework.context.support.ResourceBundleMessageSource">
		<property name="basename" value="messages"/>
	</bean>

	<!-- Annotation Processors -->
	<bean class="org.springframework.orm.jpa.support.PersistenceAnnotationBeanPostProcessor" />
	<bean class="org.springframework.dao.annotation.PersistenceExceptionTranslationPostProcessor" />


	<!-- EclipseLink JPA -->
	<bean id="jpaAdapter" class="org.springframework.orm.jpa.vendor.EclipseLinkJpaVendorAdapter">
   		<property name="databasePlatform" value="org.eclipse.persistence.platform.database.MySQLPlatform" />
   		<property name="showSql" value="true" />
	</bean>

	<!-- Hibernate JPA -->
	<!--
	<bean class="org.springframework.orm.jpa.vendor.HibernateJpaVendorAdapter">
		<property name="database" value="MYSQL" />
		<property name="showSql" value="true" />
	</bean>
	-->

	<bean id="entityManagerFactory" class="org.springframework.orm.jpa.LocalContainerEntityManagerFactoryBean">
		<property name="dataSource" ref="dataSource" />
		<property name="jpaVendorAdapter" ref="jpaAdapter" />
	</bean>

	<bean id="dataSource" class="org.springframework.jdbc.datasource.DriverManagerDataSource">
		<property name="driverClassName"><value>${jdbc.driverClassName}</value></property>
		<property name="url"><value>${jdbc.url}</value></property>
		<property name="username"><value>${jdbc.username}</value></property>
		<property name="password"><value>${jdbc.password}</value></property>
	</bean>

	<!-- DAO's 	-->
	<bean id="userDao" class="org.sloth.persistence.impl.UserDaoImpl" />
	<bean id="coordinateDao" class="org.sloth.persistence.impl.CoordinateDaoImpl" />
	<bean id="observationDao" class="org.sloth.persistence.impl.ObservationDaoImpl" />
	<bean id="observationCategorieDao" class="org.sloth.persistence.impl.ObservationCategorieDaoImpl" />

	<!-- Services -->
	<bean id="observationManager" class="org.sloth.service.impl.ObservationManagerImpl">
		<property name="observationDao" ref="observationDao" />
		<property name="coordinateDao" ref="coordinateDao" />
		<property name="observationCategorieDao" ref="observationCategorieDao" />
	</bean>

	<bean id="userManager" class="org.sloth.service.impl.UserManagerImpl">
		<property name="userDao" ref="userDao" />
	</bean>

	<bean id="passwordManager" class="org.sloth.service.impl.PasswordManagerImpl" />

</beans>